f1_weather/__init__.py
f1_weather/_exceptions.py
f1_weather/_fixes.py
f1_weather/_types.py
f1_weather/events.py
f1_weather/location.py
f1_weather/main.py
f1_weather/weather.py
f1_weather-0.1.1.dist-info/LICENSE
f1_weather-0.1.1.dist-info/METADATA
f1_weather-0.1.1.dist-info/WHEEL
f1_weather-0.1.1.dist-info/RECORD
